{
  "nodes": [
    {
      "data": {
        "name": "TO LT15",
        "orientation": "0",
        "id": "1",
        "createdAt": "2014-10-11T04:06:27.000Z",
        "updatedAt": "2014-10-11T04:06:27.000Z"
      },
      "position": {
        "x": 0,
        "y": 1260,
        "z": 0
      },
      "locked": true
    },
    {
      "data": {
        "name": "Seminar Room 6",
        "orientation": "0",
        "id": "6",
        "createdAt": "2014-10-11T04:06:27.000Z",
        "updatedAt": "2014-10-11T04:06:27.000Z"
      },
      "position": {
        "x": 1420,
        "y": 1440,
        "z": 0
      },
      "locked": true
    },
    {
      "data": {
        "name": "P2",
        "orientation": "0",
        "id": "2",
        "createdAt": "2014-10-11T04:06:27.000Z",
        "updatedAt": "2014-10-11T04:06:27.000Z"
      },
      "position": {
        "x": 1060,
        "y": 1260,
        "z": 0
      },
      "locked": true
    },
    {
      "data": {
        "name": "Linkway",
        "orientation": "0",
        "id": "3",
        "createdAt": "2014-10-11T04:06:27.000Z",
        "updatedAt": "2014-10-11T04:06:27.000Z"
      },
      "position": {
        "x": 1060,
        "y": 360,
        "z": 0
      },
      "locked": true
    },
    {
      "data": {
        "name": "P4",
        "orientation": "0",
        "id": "4",
        "createdAt": "2014-10-11T04:06:27.000Z",
        "updatedAt": "2014-10-11T04:06:27.000Z"
      },
      "position": {
        "x": 1420,
        "y": 1260,
        "z": 0
      },
      "locked": true
    },
    {
      "data": {
        "name": "P5",
        "orientation": "0",
        "id": "5",
        "createdAt": "2014-10-11T04:06:27.000Z",
        "updatedAt": "2014-10-11T04:06:27.000Z"
      },
      "position": {
        "x": 1420,
        "y": 780,
        "z": 0
      },
      "locked": true
    },
    {
      "data": {
        "name": "lobby ",
        "orientation": "0",
        "id": "7",
        "createdAt": "2014-10-11T04:06:27.000Z",
        "updatedAt": "2014-10-11T04:06:27.000Z"
      },
      "position": {
        "x": 1860,
        "y": 1260,
        "z": 0
      },
      "locked": true
    },
    {
      "data": {
        "name": "P8",
        "orientation": "0",
        "id": "8",
        "createdAt": "2014-10-11T04:06:27.000Z",
        "updatedAt": "2014-10-11T04:06:27.000Z"
      },
      "position": {
        "x": 1640,
        "y": 780,
        "z": 0
      },
      "locked": true
    },
    {
      "data": {
        "name": "Seminar Room 2",
        "orientation": "0",
        "id": "9",
        "createdAt": "2014-10-11T04:06:27.000Z",
        "updatedAt": "2014-10-11T04:06:27.000Z"
      },
      "position": {
        "x": 1640,
        "y": 460,
        "z": 0
      },
      "locked": true
    },
    {
      "data": {
        "name": "P10",
        "orientation": "0",
        "id": "10",
        "createdAt": "2014-10-11T04:06:27.000Z",
        "updatedAt": "2014-10-11T04:06:27.000Z"
      },
      "position": {
        "x": 1860,
        "y": 780,
        "z": 0
      },
      "locked": true
    },
    {
      "data": {
        "name": "Student Area",
        "orientation": "0",
        "id": "11",
        "createdAt": "2014-10-11T04:06:27.000Z",
        "updatedAt": "2014-10-11T04:06:27.000Z"
      },
      "position": {
        "x": 2760,
        "y": 780,
        "z": 0
      },
      "locked": true
    },
    {
      "data": {
        "name": "Seminar Room 1",
        "orientation": "0",
        "id": "12",
        "createdAt": "2014-10-11T04:06:27.000Z",
        "updatedAt": "2014-10-11T04:06:27.000Z"
      },
      "position": {
        "x": 2760,
        "y": 1440,
        "z": 0
      },
      "locked": true
    },
    {
      "data": {
        "name": "P13",
        "orientation": "0",
        "id": "13",
        "createdAt": "2014-10-11T04:06:27.000Z",
        "updatedAt": "2014-10-11T04:06:27.000Z"
      },
      "position": {
        "x": 2760,
        "y": 360,
        "z": 0
      },
      "locked": true
    },
    {
      "data": {
        "name": "P14",
        "orientation": "0",
        "id": "14",
        "createdAt": "2014-10-11T04:06:27.000Z",
        "updatedAt": "2014-10-11T04:06:27.000Z"
      },
      "position": {
        "x": 3480,
        "y": 780,
        "z": 0
      },
      "locked": true
    },
    {
      "data": {
        "name": "P15",
        "orientation": "0",
        "id": "15",
        "createdAt": "2014-10-11T04:06:27.000Z",
        "updatedAt": "2014-10-11T04:06:27.000Z"
      },
      "position": {
        "x": 3480,
        "y": 1380,
        "z": 0
      },
      "locked": true
    },
    {
      "data": {
        "name": "P16",
        "orientation": "0",
        "id": "16",
        "createdAt": "2014-10-11T04:06:27.000Z",
        "updatedAt": "2014-10-11T04:06:27.000Z"
      },
      "position": {
        "x": 3480,
        "y": 360,
        "z": 0
      },
      "locked": true
    },
    {
      "data": {
        "name": "P17",
        "orientation": "0",
        "id": "17",
        "createdAt": "2014-10-11T04:06:27.000Z",
        "updatedAt": "2014-10-11T04:06:27.000Z"
      },
      "position": {
        "x": 4440,
        "y": 1380,
        "z": 0
      },
      "locked": true
    },
    {
      "data": {
        "name": "P18",
        "orientation": "0",
        "id": "18",
        "createdAt": "2014-10-11T04:06:27.000Z",
        "updatedAt": "2014-10-11T04:06:27.000Z"
      },
      "position": {
        "x": 4080,
        "y": 360,
        "z": 0
      },
      "locked": true
    },
    {
      "data": {
        "name": "Executive Classroom",
        "orientation": "0",
        "id": "19",
        "createdAt": "2014-10-11T04:06:27.000Z",
        "updatedAt": "2014-10-11T04:06:27.000Z"
      },
      "position": {
        "x": 4440,
        "y": 1080,
        "z": 0
      },
      "locked": true
    },
    {
      "data": {
        "name": "Tutorial Room 8",
        "orientation": "0",
        "id": "20",
        "createdAt": "2014-10-11T04:06:27.000Z",
        "updatedAt": "2014-10-11T04:06:27.000Z"
      },
      "position": {
        "x": 4080,
        "y": 520,
        "z": 0
      },
      "locked": true
    },
    {
      "data": {
        "name": "P21",
        "orientation": "0",
        "id": "21",
        "createdAt": "2014-10-11T04:06:27.000Z",
        "updatedAt": "2014-10-11T04:06:27.000Z"
      },
      "position": {
        "x": 4660,
        "y": 1380,
        "z": 0
      },
      "locked": true
    },
    {
      "data": {
        "name": "P22",
        "orientation": "0",
        "id": "22",
        "createdAt": "2014-10-11T04:06:27.000Z",
        "updatedAt": "2014-10-11T04:06:27.000Z"
      },
      "position": {
        "x": 4800,
        "y": 360,
        "z": 0
      },
      "locked": true
    },
    {
      "data": {
        "name": "Seminar Room 9",
        "orientation": "0",
        "id": "23",
        "createdAt": "2014-10-11T04:06:27.000Z",
        "updatedAt": "2014-10-11T04:06:27.000Z"
      },
      "position": {
        "x": 4660,
        "y": 1600,
        "z": 0
      },
      "locked": true
    },
    {
      "data": {
        "name": "P24",
        "orientation": "0",
        "id": "24",
        "createdAt": "2014-10-11T04:06:27.000Z",
        "updatedAt": "2014-10-11T04:06:27.000Z"
      },
      "position": {
        "x": 5220,
        "y": 1380,
        "z": 0
      },
      "locked": true
    },
    {
      "data": {
        "name": "Tutorial Room 9",
        "orientation": "0",
        "id": "25",
        "createdAt": "2014-10-11T04:06:27.000Z",
        "updatedAt": "2014-10-11T04:06:27.000Z"
      },
      "position": {
        "x": 4800,
        "y": 520,
        "z": 0
      },
      "locked": true
    },
    {
      "data": {
        "name": "P26",
        "orientation": "0",
        "id": "26",
        "createdAt": "2014-10-11T04:06:27.000Z",
        "updatedAt": "2014-10-11T04:06:27.000Z"
      },
      "position": {
        "x": 5220,
        "y": 360,
        "z": 0
      },
      "locked": true
    },
    {
      "data": {
        "name": "Seminar Room 11",
        "orientation": "0",
        "id": "27",
        "createdAt": "2014-10-11T04:06:27.000Z",
        "updatedAt": "2014-10-11T04:06:27.000Z"
      },
      "position": {
        "x": 5220,
        "y": 1600,
        "z": 0
      },
      "locked": true
    },
    {
      "data": {
        "name": "P28",
        "orientation": "0",
        "id": "28",
        "createdAt": "2014-10-11T04:06:27.000Z",
        "updatedAt": "2014-10-11T04:06:27.000Z"
      },
      "position": {
        "x": 5220,
        "y": 620,
        "z": 0
      },
      "locked": true
    },
    {
      "data": {
        "name": "P29",
        "orientation": "0",
        "id": "29",
        "createdAt": "2014-10-11T04:06:27.000Z",
        "updatedAt": "2014-10-11T04:06:27.000Z"
      },
      "position": {
        "x": 5700,
        "y": 360,
        "z": 0
      },
      "locked": true
    },
    {
      "data": {
        "name": "TO Canteen",
        "orientation": "0",
        "id": "30",
        "createdAt": "2014-10-11T04:06:27.000Z",
        "updatedAt": "2014-10-11T04:06:27.000Z"
      },
      "position": {
        "x": 6000,
        "y": 360,
        "z": 0
      },
      "locked": true
    },
    {
      "data": {
        "name": "TO COM2-2",
        "orientation": "0",
        "id": "31",
        "createdAt": "2014-10-11T04:06:27.000Z",
        "updatedAt": "2014-10-11T04:06:27.000Z"
      },
      "position": {
        "x": 5800,
        "y": 240,
        "z": 0
      },
      "locked": true
    },
    {
      "data": {
        "name": "person",
        "orientation": "0.0",
        "id": "-1",
        "createdAt": "2014-10-15T09:24:52.000Z",
        "updatedAt": "2014-10-22T09:42:31.000Z"
      },
      "position": {
        "x": 0,
        "y": 0,
        "z": 0
      },
      "locked": true
    }
  ],
  "edges": [
    {
      "data": {
        "name": "edge",
        "source": "2",
        "target": "4",
        "weight": 360,
        "interaction": "undirected",
        "shared_interaction": "undirected",
        "id": "idx1e2",
        "createdAt": "2014-10-11T04:06:27.000Z",
        "updatedAt": "2014-10-11T04:06:27.000Z"
      }
    },
    {
      "data": {
        "name": "edge",
        "source": "3",
        "target": "2",
        "weight": 900,
        "interaction": "undirected",
        "shared_interaction": "undirected",
        "id": "idx2e0",
        "createdAt": "2014-10-11T04:06:27.000Z",
        "updatedAt": "2014-10-11T04:06:27.000Z"
      }
    },
    {
      "data": {
        "name": "edge",
        "source": "1",
        "target": "2",
        "weight": 1060,
        "interaction": "undirected",
        "shared_interaction": "undirected",
        "id": "idx0e0",
        "createdAt": "2014-10-11T04:06:27.000Z",
        "updatedAt": "2014-10-11T04:06:27.000Z"
      }
    },
    {
      "data": {
        "name": "edge",
        "source": "2",
        "target": "1",
        "weight": 1060,
        "interaction": "undirected",
        "shared_interaction": "undirected",
        "id": "idx1e0",
        "createdAt": "2014-10-11T04:06:27.000Z",
        "updatedAt": "2014-10-11T04:06:27.000Z"
      }
    },
    {
      "data": {
        "name": "edge",
        "source": "2",
        "target": "3",
        "weight": 900,
        "interaction": "undirected",
        "shared_interaction": "undirected",
        "id": "idx1e1",
        "createdAt": "2014-10-11T04:06:27.000Z",
        "updatedAt": "2014-10-11T04:06:27.000Z"
      }
    },
    {
      "data": {
        "name": "edge",
        "source": "4",
        "target": "2",
        "weight": 360,
        "interaction": "undirected",
        "shared_interaction": "undirected",
        "id": "idx3e0",
        "createdAt": "2014-10-11T04:06:27.000Z",
        "updatedAt": "2014-10-11T04:06:27.000Z"
      }
    },
    {
      "data": {
        "name": "edge",
        "source": "4",
        "target": "5",
        "weight": 480,
        "interaction": "undirected",
        "shared_interaction": "undirected",
        "id": "idx3e1",
        "createdAt": "2014-10-11T04:06:27.000Z",
        "updatedAt": "2014-10-11T04:06:27.000Z"
      }
    },
    {
      "data": {
        "name": "edge",
        "source": "4",
        "target": "6",
        "weight": 180,
        "interaction": "undirected",
        "shared_interaction": "undirected",
        "id": "idx3e2",
        "createdAt": "2014-10-11T04:06:27.000Z",
        "updatedAt": "2014-10-11T04:06:27.000Z"
      }
    },
    {
      "data": {
        "name": "edge",
        "source": "4",
        "target": "7",
        "weight": 440,
        "interaction": "undirected",
        "shared_interaction": "undirected",
        "id": "idx3e3",
        "createdAt": "2014-10-11T04:06:27.000Z",
        "updatedAt": "2014-10-11T04:06:27.000Z"
      }
    },
    {
      "data": {
        "name": "edge",
        "source": "5",
        "target": "4",
        "weight": 480,
        "interaction": "undirected",
        "shared_interaction": "undirected",
        "id": "idx4e0",
        "createdAt": "2014-10-11T04:06:27.000Z",
        "updatedAt": "2014-10-11T04:06:27.000Z"
      }
    },
    {
      "data": {
        "name": "edge",
        "source": "5",
        "target": "8",
        "weight": 220,
        "interaction": "undirected",
        "shared_interaction": "undirected",
        "id": "idx4e1",
        "createdAt": "2014-10-11T04:06:27.000Z",
        "updatedAt": "2014-10-11T04:06:27.000Z"
      }
    },
    {
      "data": {
        "name": "edge",
        "source": "6",
        "target": "4",
        "weight": 180,
        "interaction": "undirected",
        "shared_interaction": "undirected",
        "id": "idx5e0",
        "createdAt": "2014-10-11T04:06:27.000Z",
        "updatedAt": "2014-10-11T04:06:27.000Z"
      }
    },
    {
      "data": {
        "name": "edge",
        "source": "7",
        "target": "4",
        "weight": 440,
        "interaction": "undirected",
        "shared_interaction": "undirected",
        "id": "idx6e0",
        "createdAt": "2014-10-11T04:06:27.000Z",
        "updatedAt": "2014-10-11T04:06:27.000Z"
      }
    },
    {
      "data": {
        "name": "edge",
        "source": "7",
        "target": "10",
        "weight": 480,
        "interaction": "undirected",
        "shared_interaction": "undirected",
        "id": "idx6e1",
        "createdAt": "2014-10-11T04:06:27.000Z",
        "updatedAt": "2014-10-11T04:06:27.000Z"
      }
    },
    {
      "data": {
        "name": "edge",
        "source": "8",
        "target": "5",
        "weight": 220,
        "interaction": "undirected",
        "shared_interaction": "undirected",
        "id": "idx7e0",
        "createdAt": "2014-10-11T04:06:27.000Z",
        "updatedAt": "2014-10-11T04:06:27.000Z"
      }
    },
    {
      "data": {
        "name": "edge",
        "source": "8",
        "target": "9",
        "weight": 320,
        "interaction": "undirected",
        "shared_interaction": "undirected",
        "id": "idx7e1",
        "createdAt": "2014-10-11T04:06:27.000Z",
        "updatedAt": "2014-10-11T04:06:27.000Z"
      }
    },
    {
      "data": {
        "name": "edge",
        "source": "8",
        "target": "10",
        "weight": 220,
        "interaction": "undirected",
        "shared_interaction": "undirected",
        "id": "idx7e2",
        "createdAt": "2014-10-11T04:06:27.000Z",
        "updatedAt": "2014-10-11T04:06:27.000Z"
      }
    },
    {
      "data": {
        "name": "edge",
        "source": "9",
        "target": "8",
        "weight": 320,
        "interaction": "undirected",
        "shared_interaction": "undirected",
        "id": "idx8e0",
        "createdAt": "2014-10-11T04:06:27.000Z",
        "updatedAt": "2014-10-11T04:06:27.000Z"
      }
    },
    {
      "data": {
        "name": "edge",
        "source": "10",
        "target": "7",
        "weight": 480,
        "interaction": "undirected",
        "shared_interaction": "undirected",
        "id": "idx9e0",
        "createdAt": "2014-10-11T04:06:27.000Z",
        "updatedAt": "2014-10-11T04:06:27.000Z"
      }
    },
    {
      "data": {
        "name": "edge",
        "source": "10",
        "target": "8",
        "weight": 220,
        "interaction": "undirected",
        "shared_interaction": "undirected",
        "id": "idx9e1",
        "createdAt": "2014-10-11T04:06:27.000Z",
        "updatedAt": "2014-10-11T04:06:27.000Z"
      }
    },
    {
      "data": {
        "name": "edge",
        "source": "10",
        "target": "11",
        "weight": 900,
        "interaction": "undirected",
        "shared_interaction": "undirected",
        "id": "idx9e2",
        "createdAt": "2014-10-11T04:06:27.000Z",
        "updatedAt": "2014-10-11T04:06:27.000Z"
      }
    },
    {
      "data": {
        "name": "edge",
        "source": "11",
        "target": "10",
        "weight": 900,
        "interaction": "undirected",
        "shared_interaction": "undirected",
        "id": "idx10e0",
        "createdAt": "2014-10-11T04:06:27.000Z",
        "updatedAt": "2014-10-11T04:06:27.000Z"
      }
    },
    {
      "data": {
        "name": "edge",
        "source": "11",
        "target": "12",
        "weight": 660,
        "interaction": "undirected",
        "shared_interaction": "undirected",
        "id": "idx10e1",
        "createdAt": "2014-10-11T04:06:27.000Z",
        "updatedAt": "2014-10-11T04:06:27.000Z"
      }
    },
    {
      "data": {
        "name": "edge",
        "source": "11",
        "target": "13",
        "weight": 420,
        "interaction": "undirected",
        "shared_interaction": "undirected",
        "id": "idx10e2",
        "createdAt": "2014-10-11T04:06:27.000Z",
        "updatedAt": "2014-10-11T04:06:27.000Z"
      }
    },
    {
      "data": {
        "name": "edge",
        "source": "11",
        "target": "14",
        "weight": 720,
        "interaction": "undirected",
        "shared_interaction": "undirected",
        "id": "idx10e3",
        "createdAt": "2014-10-11T04:06:27.000Z",
        "updatedAt": "2014-10-11T04:06:27.000Z"
      }
    },
    {
      "data": {
        "name": "edge",
        "source": "12",
        "target": "11",
        "weight": 660,
        "interaction": "undirected",
        "shared_interaction": "undirected",
        "id": "idx11e0",
        "createdAt": "2014-10-11T04:06:27.000Z",
        "updatedAt": "2014-10-11T04:06:27.000Z"
      }
    },
    {
      "data": {
        "name": "edge",
        "source": "13",
        "target": "11",
        "weight": 420,
        "interaction": "undirected",
        "shared_interaction": "undirected",
        "id": "idx12e0",
        "createdAt": "2014-10-11T04:06:27.000Z",
        "updatedAt": "2014-10-11T04:06:27.000Z"
      }
    },
    {
      "data": {
        "name": "edge",
        "source": "14",
        "target": "11",
        "weight": 720,
        "interaction": "undirected",
        "shared_interaction": "undirected",
        "id": "idx13e0",
        "createdAt": "2014-10-11T04:06:27.000Z",
        "updatedAt": "2014-10-11T04:06:27.000Z"
      }
    },
    {
      "data": {
        "name": "edge",
        "source": "14",
        "target": "15",
        "weight": 600,
        "interaction": "undirected",
        "shared_interaction": "undirected",
        "id": "idx13e1",
        "createdAt": "2014-10-11T04:06:27.000Z",
        "updatedAt": "2014-10-11T04:06:27.000Z"
      }
    },
    {
      "data": {
        "name": "edge",
        "source": "14",
        "target": "16",
        "weight": 420,
        "interaction": "undirected",
        "shared_interaction": "undirected",
        "id": "idx13e2",
        "createdAt": "2014-10-11T04:06:27.000Z",
        "updatedAt": "2014-10-11T04:06:27.000Z"
      }
    },
    {
      "data": {
        "name": "edge",
        "source": "15",
        "target": "14",
        "weight": 600,
        "interaction": "undirected",
        "shared_interaction": "undirected",
        "id": "idx14e0",
        "createdAt": "2014-10-11T04:06:27.000Z",
        "updatedAt": "2014-10-11T04:06:27.000Z"
      }
    },
    {
      "data": {
        "name": "edge",
        "source": "15",
        "target": "17",
        "weight": 960,
        "interaction": "undirected",
        "shared_interaction": "undirected",
        "id": "idx14e1",
        "createdAt": "2014-10-11T04:06:27.000Z",
        "updatedAt": "2014-10-11T04:06:27.000Z"
      }
    },
    {
      "data": {
        "name": "edge",
        "source": "16",
        "target": "14",
        "weight": 420,
        "interaction": "undirected",
        "shared_interaction": "undirected",
        "id": "idx15e0",
        "createdAt": "2014-10-11T04:06:27.000Z",
        "updatedAt": "2014-10-11T04:06:27.000Z"
      }
    },
    {
      "data": {
        "name": "edge",
        "source": "16",
        "target": "18",
        "weight": 600,
        "interaction": "undirected",
        "shared_interaction": "undirected",
        "id": "idx15e1",
        "createdAt": "2014-10-11T04:06:27.000Z",
        "updatedAt": "2014-10-11T04:06:27.000Z"
      }
    },
    {
      "data": {
        "name": "edge",
        "source": "17",
        "target": "15",
        "weight": 960,
        "interaction": "undirected",
        "shared_interaction": "undirected",
        "id": "idx16e0",
        "createdAt": "2014-10-11T04:06:27.000Z",
        "updatedAt": "2014-10-11T04:06:27.000Z"
      }
    },
    {
      "data": {
        "name": "edge",
        "source": "17",
        "target": "19",
        "weight": 300,
        "interaction": "undirected",
        "shared_interaction": "undirected",
        "id": "idx16e1",
        "createdAt": "2014-10-11T04:06:27.000Z",
        "updatedAt": "2014-10-11T04:06:27.000Z"
      }
    },
    {
      "data": {
        "name": "edge",
        "source": "17",
        "target": "21",
        "weight": 220,
        "interaction": "undirected",
        "shared_interaction": "undirected",
        "id": "idx16e2",
        "createdAt": "2014-10-11T04:06:27.000Z",
        "updatedAt": "2014-10-11T04:06:27.000Z"
      }
    },
    {
      "data": {
        "name": "edge",
        "source": "18",
        "target": "16",
        "weight": 600,
        "interaction": "undirected",
        "shared_interaction": "undirected",
        "id": "idx17e0",
        "createdAt": "2014-10-11T04:06:27.000Z",
        "updatedAt": "2014-10-11T04:06:27.000Z"
      }
    },
    {
      "data": {
        "name": "edge",
        "source": "18",
        "target": "20",
        "weight": 160,
        "interaction": "undirected",
        "shared_interaction": "undirected",
        "id": "idx17e1",
        "createdAt": "2014-10-11T04:06:27.000Z",
        "updatedAt": "2014-10-11T04:06:27.000Z"
      }
    },
    {
      "data": {
        "name": "edge",
        "source": "18",
        "target": "22",
        "weight": 720,
        "interaction": "undirected",
        "shared_interaction": "undirected",
        "id": "idx17e2",
        "createdAt": "2014-10-11T04:06:27.000Z",
        "updatedAt": "2014-10-11T04:06:27.000Z"
      }
    },
    {
      "data": {
        "name": "edge",
        "source": "19",
        "target": "17",
        "weight": 300,
        "interaction": "undirected",
        "shared_interaction": "undirected",
        "id": "idx18e0",
        "createdAt": "2014-10-11T04:06:27.000Z",
        "updatedAt": "2014-10-11T04:06:27.000Z"
      }
    },
    {
      "data": {
        "name": "edge",
        "source": "20",
        "target": "18",
        "weight": 160,
        "interaction": "undirected",
        "shared_interaction": "undirected",
        "id": "idx19e0",
        "createdAt": "2014-10-11T04:06:27.000Z",
        "updatedAt": "2014-10-11T04:06:27.000Z"
      }
    },
    {
      "data": {
        "name": "edge",
        "source": "21",
        "target": "17",
        "weight": 220,
        "interaction": "undirected",
        "shared_interaction": "undirected",
        "id": "idx20e0",
        "createdAt": "2014-10-11T04:06:27.000Z",
        "updatedAt": "2014-10-11T04:06:27.000Z"
      }
    },
    {
      "data": {
        "name": "edge",
        "source": "21",
        "target": "23",
        "weight": 220,
        "interaction": "undirected",
        "shared_interaction": "undirected",
        "id": "idx20e1",
        "createdAt": "2014-10-11T04:06:27.000Z",
        "updatedAt": "2014-10-11T04:06:27.000Z"
      }
    },
    {
      "data": {
        "name": "edge",
        "source": "21",
        "target": "24",
        "weight": 560,
        "interaction": "undirected",
        "shared_interaction": "undirected",
        "id": "idx20e2",
        "createdAt": "2014-10-11T04:06:27.000Z",
        "updatedAt": "2014-10-11T04:06:27.000Z"
      }
    },
    {
      "data": {
        "name": "edge",
        "source": "22",
        "target": "18",
        "weight": 720,
        "interaction": "undirected",
        "shared_interaction": "undirected",
        "id": "idx21e0",
        "createdAt": "2014-10-11T04:06:27.000Z",
        "updatedAt": "2014-10-11T04:06:27.000Z"
      }
    },
    {
      "data": {
        "name": "edge",
        "source": "22",
        "target": "25",
        "weight": 160,
        "interaction": "undirected",
        "shared_interaction": "undirected",
        "id": "idx21e1",
        "createdAt": "2014-10-11T04:06:27.000Z",
        "updatedAt": "2014-10-11T04:06:27.000Z"
      }
    },
    {
      "data": {
        "name": "edge",
        "source": "22",
        "target": "26",
        "weight": 420,
        "interaction": "undirected",
        "shared_interaction": "undirected",
        "id": "idx21e2",
        "createdAt": "2014-10-11T04:06:27.000Z",
        "updatedAt": "2014-10-11T04:06:27.000Z"
      }
    },
    {
      "data": {
        "name": "edge",
        "source": "23",
        "target": "21",
        "weight": 220,
        "interaction": "undirected",
        "shared_interaction": "undirected",
        "id": "idx22e0",
        "createdAt": "2014-10-11T04:06:27.000Z",
        "updatedAt": "2014-10-11T04:06:27.000Z"
      }
    },
    {
      "data": {
        "name": "edge",
        "source": "24",
        "target": "21",
        "weight": 560,
        "interaction": "undirected",
        "shared_interaction": "undirected",
        "id": "idx23e0",
        "createdAt": "2014-10-11T04:06:27.000Z",
        "updatedAt": "2014-10-11T04:06:27.000Z"
      }
    },
    {
      "data": {
        "name": "edge",
        "source": "24",
        "target": "27",
        "weight": 220,
        "interaction": "undirected",
        "shared_interaction": "undirected",
        "id": "idx23e1",
        "createdAt": "2014-10-11T04:06:27.000Z",
        "updatedAt": "2014-10-11T04:06:27.000Z"
      }
    },
    {
      "data": {
        "name": "edge",
        "source": "24",
        "target": "28",
        "weight": 760,
        "interaction": "undirected",
        "shared_interaction": "undirected",
        "id": "idx23e2",
        "createdAt": "2014-10-11T04:06:27.000Z",
        "updatedAt": "2014-10-11T04:06:27.000Z"
      }
    },
    {
      "data": {
        "name": "edge",
        "source": "25",
        "target": "22",
        "weight": 160,
        "interaction": "undirected",
        "shared_interaction": "undirected",
        "id": "idx24e0",
        "createdAt": "2014-10-11T04:06:27.000Z",
        "updatedAt": "2014-10-11T04:06:27.000Z"
      }
    },
    {
      "data": {
        "name": "edge",
        "source": "26",
        "target": "22",
        "weight": 420,
        "interaction": "undirected",
        "shared_interaction": "undirected",
        "id": "idx25e0",
        "createdAt": "2014-10-11T04:06:27.000Z",
        "updatedAt": "2014-10-11T04:06:27.000Z"
      }
    },
    {
      "data": {
        "name": "edge",
        "source": "26",
        "target": "28",
        "weight": 260,
        "interaction": "undirected",
        "shared_interaction": "undirected",
        "id": "idx25e1",
        "createdAt": "2014-10-11T04:06:27.000Z",
        "updatedAt": "2014-10-11T04:06:27.000Z"
      }
    },
    {
      "data": {
        "name": "edge",
        "source": "26",
        "target": "29",
        "weight": 480,
        "interaction": "undirected",
        "shared_interaction": "undirected",
        "id": "idx25e2",
        "createdAt": "2014-10-11T04:06:27.000Z",
        "updatedAt": "2014-10-11T04:06:27.000Z"
      }
    },
    {
      "data": {
        "name": "edge",
        "source": "27",
        "target": "24",
        "weight": 220,
        "interaction": "undirected",
        "shared_interaction": "undirected",
        "id": "idx26e0",
        "createdAt": "2014-10-11T04:06:27.000Z",
        "updatedAt": "2014-10-11T04:06:27.000Z"
      }
    },
    {
      "data": {
        "name": "edge",
        "source": "28",
        "target": "24",
        "weight": 760,
        "interaction": "undirected",
        "shared_interaction": "undirected",
        "id": "idx27e0",
        "createdAt": "2014-10-11T04:06:27.000Z",
        "updatedAt": "2014-10-11T04:06:27.000Z"
      }
    },
    {
      "data": {
        "name": "edge",
        "source": "28",
        "target": "26",
        "weight": 260,
        "interaction": "undirected",
        "shared_interaction": "undirected",
        "id": "idx27e1",
        "createdAt": "2014-10-11T04:06:27.000Z",
        "updatedAt": "2014-10-11T04:06:27.000Z"
      }
    },
    {
      "data": {
        "name": "edge",
        "source": "28",
        "target": "30",
        "weight": 822.192,
        "interaction": "undirected",
        "shared_interaction": "undirected",
        "id": "idx27e2",
        "createdAt": "2014-10-11T04:06:27.000Z",
        "updatedAt": "2014-10-11T04:06:27.000Z"
      }
    },
    {
      "data": {
        "name": "edge",
        "source": "29",
        "target": "26",
        "weight": 480,
        "interaction": "undirected",
        "shared_interaction": "undirected",
        "id": "idx28e0",
        "createdAt": "2014-10-11T04:06:27.000Z",
        "updatedAt": "2014-10-11T04:06:27.000Z"
      }
    },
    {
      "data": {
        "name": "edge",
        "source": "29",
        "target": "31",
        "weight": 156.205,
        "interaction": "undirected",
        "shared_interaction": "undirected",
        "id": "idx28e1",
        "createdAt": "2014-10-11T04:06:27.000Z",
        "updatedAt": "2014-10-11T04:06:27.000Z"
      }
    },
    {
      "data": {
        "name": "edge",
        "source": "30",
        "target": "28",
        "weight": 822.192,
        "interaction": "undirected",
        "shared_interaction": "undirected",
        "id": "idx29e0",
        "createdAt": "2014-10-11T04:06:27.000Z",
        "updatedAt": "2014-10-11T04:06:27.000Z"
      }
    },
    {
      "data": {
        "name": "edge",
        "source": "31",
        "target": "29",
        "weight": 156.205,
        "interaction": "undirected",
        "shared_interaction": "undirected",
        "id": "idx30e0",
        "createdAt": "2014-10-11T04:06:27.000Z",
        "updatedAt": "2014-10-11T04:06:27.000Z"
      }
    }
  ]
}